setup.py
codemod/__init__.py
codemod/base.py
codemod.egg-info/PKG-INFO
codemod.egg-info/SOURCES.txt
codemod.egg-info/dependency_links.txt
codemod.egg-info/entry_points.txt
codemod.egg-info/not-zip-safe
codemod.egg-info/top_level.txt